{
    "result":"success",
    "templates":[
        {
            "template_id": "66427ed4c32512b07bba63a3",
            "name": "Template Estrella Update Prueba definitiva prueba",
            "created_at": "2024-05-25T12:00:00Z",
            "description": "Template con topologÃa tipo estrella"
        },
        {
            "template_id": "66427ed4c32512b07bba6334",
            "name": "Template 2 U",
            "created_at": "2024-05-25T12:00:00Z",
            "description": "2"
        }
    ]
}
